src/__init__.py
src/uniqchars3/__init__.py
src/uniqchars3/main.py
src/uniqchars3/app/__init__.py
src/uniqchars3/app/app.py
src/uniqchars3/utils/__init__.py
src/uniqchars3/utils/exceptions.py
src/uniqchars3/utils/functions.py
tests/__init__.py
uniqchars3-1.3.dist-info/LICENSE
uniqchars3-1.3.dist-info/METADATA
uniqchars3-1.3.dist-info/WHEEL
uniqchars3-1.3.dist-info/entry_points.txt
uniqchars3-1.3.dist-info/top_level.txt
uniqchars3-1.3.dist-info/RECORD
